ariel_data_preprocessing/README.md
ariel_data_preprocessing/__init__.py
ariel_data_preprocessing/calibration_data.py
ariel_data_preprocessing/data_generator_functions.py
ariel_data_preprocessing/data_preprocessing.py
ariel_data_preprocessing/difference_pair_generator_functions.py
ariel_data_preprocessing/signal_correction_functions.py
ariel_data_preprocessing/signal_extraction_functions.py
ariel_data_preprocessing/transit_differencing.py
ariel_data_preprocessing/utils.py
ariel_data_preprocessing-1.5.dist-info/METADATA
ariel_data_preprocessing-1.5.dist-info/WHEEL
ariel_data_preprocessing-1.5.dist-info/RECORD
