Metadata-Version: 2.4
Name: ariel_data_preprocessing
Version: 1.5
Summary: Signal correction module for Ariel Data Challenge 2025.
Project-URL: Homepage, https://github.com/gperdrizet/ariel-data-challenge
Project-URL: Issues, https://github.com/gperdrizet/ariel-data-challenge/issues
Author-email: George Perdrizet <george@perdrizet.org>
License-Expression: GPL-3.0-or-later
Classifier: Operating System :: OS Independent
Classifier: Programming Language :: Python :: 3
Requires-Python: >=3.8
Requires-Dist: astropy
Requires-Dist: hdf5
Requires-Dist: numpy
Requires-Dist: pandas
Requires-Dist: pyarrow
Requires-Dist: scipy
Requires-Dist: tensorflow
